{
  "routes": [
    {
      "method": "GET",
      "path": "/partners-frs",
      "handler": "partners-fr.find",
      "config": {
        "policies": []
      }
    },
    {
      "method": "GET",
      "path": "/partners-frs/count",
      "handler": "partners-fr.count",
      "config": {
        "policies": []
      }
    },
    {
      "method": "GET",
      "path": "/partners-frs/:id",
      "handler": "partners-fr.findOne",
      "config": {
        "policies": []
      }
    },
    {
      "method": "POST",
      "path": "/partners-frs",
      "handler": "partners-fr.create",
      "config": {
        "policies": []
      }
    },
    {
      "method": "PUT",
      "path": "/partners-frs/:id",
      "handler": "partners-fr.update",
      "config": {
        "policies": []
      }
    },
    {
      "method": "DELETE",
      "path": "/partners-frs/:id",
      "handler": "partners-fr.delete",
      "config": {
        "policies": []
      }
    }
  ]
}
